side_effects/__init__.py
side_effects/apps.py
side_effects/checks.py
side_effects/decorators.py
side_effects/management/__init__.py
side_effects/management/commands/__init__.py
side_effects/management/commands/display_side_effects.py
side_effects/registry.py
side_effects/settings.py
side_effects-1.6.dev0.dist-info/LICENSE
side_effects-1.6.dev0.dist-info/WHEEL
side_effects-1.6.dev0.dist-info/METADATA
side_effects-1.6.dev0.dist-info/RECORD
