Metadata-Version: 2.1
Name: side-effects
Version: 1.6.dev0
Summary: Django app for managing external side effects.
Home-page: https://github.com/yunojuno/poetry-template
License: MIT
Author: YunoJuno
Author-email: code@yunojuno.com
Requires-Python: >=3.6,<4.0
Classifier: Environment :: Web Environment
Classifier: Framework :: Django :: 2.2
Classifier: Framework :: Django :: 3.0
Classifier: License :: OSI Approved :: MIT License
Classifier: Operating System :: OS Independent
Classifier: Programming Language :: Python :: 3
Classifier: Programming Language :: Python :: 3.6
Classifier: Programming Language :: Python :: 3.7
Classifier: Programming Language :: Python :: 3.8
Requires-Dist: django (>=2.2,<4.0)
Requires-Dist: python-env-utils
Project-URL: Repository, https://github.com/yunojuno/poetry-template
